LICENSE
MANIFEST.in
README.rst
VERSION
pytest.ini
requirements.txt
setup.cfg
setup.py
pw_onemap/__init__.py
pw_onemap/api.py
pw_onemap/client.py
pw_onemap/exceptions.py
pw_onemap/response.py
pw_onemap/status.py
pw_onemap/utils.py
pw_onemap.egg-info/PKG-INFO
pw_onemap.egg-info/SOURCES.txt
pw_onemap.egg-info/dependency_links.txt
pw_onemap.egg-info/not-zip-safe
pw_onemap.egg-info/requires.txt
pw_onemap.egg-info/top_level.txt
tests/__init__.py
tests/test_api.py
tests/test_client.py
tests/test_response.py
tests/test_status.py
tests/test_utils.py