Metadata-Version: 1.1
Name: pw-onemap
Version: 0.1.2
Summary: OneMap SG Connector
Home-page: https://gitlab.com/
Author: willy
Author-email: loh.wilson@gmail.com
License: MIT
Platform: UNKNOWN
Classifier: Programming Language :: Python :: 3.6
Classifier: Programming Language :: Python :: 3.7
Classifier: Topic :: Software Development :: Libraries :: Python Modules
